cleanse_speech-0.1.3.dist-info/METADATA
cleanse_speech-0.1.3.dist-info/WHEEL
cleanse_speech-0.1.3.dist-info/licenses/LICENSE
cleanse_speech-0.1.3.dist-info/licenses/NOTICE.MD
cleanse_speech/__init__.py
cleanse_speech/bin/cn_advertisement.bin
cleanse_speech/bin/cn_general.bin
cleanse_speech/bin/cn_netease.bin
cleanse_speech/bin/cn_politics.bin
cleanse_speech/bin/cn_pornographic.bin
cleanse_speech/bookshelf.py
cleanse_speech/dlfa.py
cleanse_speech-0.1.3.dist-info/RECORD
