Metadata-Version: 2.1
Name: cleanse-speech
Version: 0.1.3
Summary: An intelligent Python library designed to detect and filter offensive language, ensuring respectful and constructive communication in any digital space.
Author-Email: llmkira <me@dianas.cyou>
License: MIT
Requires-Python: >=3.9
Requires-Dist: zhconv>=1.4.3
